{
  "name": "apps",
  "displayName": "Apps",
  "items": [
    {
      "name": "games",
      "displayName": "Games",
      "img": "http://192.168.3.7:4000/assets/folder.svg",
      "items": [
        {
          "name": "minecraft_launcher",
          "displayName": "Minecraft",
          "cmd": "\"C:/XboxGames/Minecraft Launcher/Content/Minecraft.exe\"",
          "img": "https://www.minecraft.net/content/dam/minecraftnet/franchise/logos/Homepage_Download-Launcher_Creeper-Logo_500x500.png"
        },
        {
          "name": "minecraft",
          "displayName": "Minecraft Bedrock",
          "cmd": "powershell.exe Start-Process minecraft:",
          "img": "https://www.minecraft.net/content/dam/minecraftnet/franchise/logos/Homepage_Download-Launcher_Creeper-Logo_500x500.png"
        },
        {
          "name": "steam",
          "displayName": "Steam",
          "cmd": "\"C:/Program Files (x86)/Steam/steam.exe\"",
          "img": "https://upload.wikimedia.org/wikipedia/commons/8/83/Steam_icon_logo.svg"
        },
        {
          "name": "factorio",
          "displayName": "Factorio",
          "cmd": "start steam://rungameid/427520",
          "img": "https://factorio.com/static/img/factorio-wheel.png"
        },
        {
          "name": "lens_island",
          "displayName": "Lens Island",
          "cmd": "start steam://rungameid/1335830",
          "img": "https://static.wixstatic.com/media/80797d_3fc2ed5d4f2b45a49dd11fc97a834e9e%7Emv2.png/v1/fill/w_192%2Ch_192%2Clg_1%2Cusm_0.66_1.00_0.01/80797d_3fc2ed5d4f2b45a49dd11fc97a834e9e%7Emv2.png"
        }
      ]
    },
    {
      "name": "smart_home",
      "displayName": "Smart Home",
      "img": "http://192.168.3.7:4000/assets/folder.svg",
      "items": []
    },
    {
      "name": "discord",
      "displayName": "Discord",
      "cmd": "C:/Users/ahlou/AppData/Roaming/Microsoft/Windows/Start Menu/Programs/Discord Inc/Discord.lnk",
      "img": "https://static.vecteezy.com/system/resources/previews/006/892/625/non_2x/discord-logo-icon-editorial-free-vector.jpg"
    },
    {
      "name": "spotify",
      "displayName": "Spotify",
      "cmd": "powershell.exe Start-Process spotify:",
      "img": "http://192.168.3.7:4000/assets/spotify.png"
    },
    {
      "name": "docker",
      "displayName": "Docker",
      "cmd": "\"C:/Program Files/Docker/Docker/Docker Desktop.exe\"",
      "img": "https://cdn4.iconfinder.com/data/icons/logos-and-brands/512/97_Docker_logo_logos-512.png"
    },
    {
      "name": "vscode",
      "displayName": "VSCode",
      "cmd": "\"C:/Users/ahlou/AppData/Local/Programs/Microsoft VS Code/Code.exe\"",
      "img": "https://code.visualstudio.com/assets/images/code-stable.png"
    },
    {
      "name": "notepad",
      "displayName": "Notepad",
      "cmd": "C:/Windows/System32/notepad.exe",
      "img": "https://upload.wikimedia.org/wikipedia/commons/c/c9/Windows_Notepad_icon.png"
    },
    {
      "name": "notepad",
      "displayName": "Notepad",
      "cmd": "C:/Windows/System32/notepad.exe",
      "img": "https://upload.wikimedia.org/wikipedia/commons/c/c9/Windows_Notepad_icon.png"
    },
    {
      "name": "notepad",
      "displayName": "Notepad",
      "cmd": "C:/Windows/System32/notepad.exe",
      "img": "https://upload.wikimedia.org/wikipedia/commons/c/c9/Windows_Notepad_icon.png"
    },
    {
      "name": "notepad",
      "displayName": "Notepad",
      "cmd": "C:/Windows/System32/notepad.exe",
      "img": "https://upload.wikimedia.org/wikipedia/commons/c/c9/Windows_Notepad_icon.png"
    },
    {
      "name": "notepad",
      "displayName": "Notepad",
      "cmd": "C:/Windows/System32/notepad.exe",
      "img": "https://upload.wikimedia.org/wikipedia/commons/c/c9/Windows_Notepad_icon.png"
    },
    {
      "name": "notepad",
      "displayName": "Notepad",
      "cmd": "C:/Windows/System32/notepad.exe",
      "img": "https://upload.wikimedia.org/wikipedia/commons/c/c9/Windows_Notepad_icon.png"
    },
    {
      "name": "notepad",
      "displayName": "Notepad",
      "cmd": "C:/Windows/System32/notepad.exe",
      "img": "https://upload.wikimedia.org/wikipedia/commons/c/c9/Windows_Notepad_icon.png"
    },
    {
      "name": "notepad",
      "displayName": "Notepad",
      "cmd": "C:/Windows/System32/notepad.exe",
      "img": "https://upload.wikimedia.org/wikipedia/commons/c/c9/Windows_Notepad_icon.png"
    },
    {
      "name": "notepad",
      "displayName": "Notepad",
      "cmd": "C:/Windows/System32/notepad.exe",
      "img": "https://upload.wikimedia.org/wikipedia/commons/c/c9/Windows_Notepad_icon.png"
    },
    {
      "name": "notepad",
      "displayName": "Notepad",
      "cmd": "C:/Windows/System32/notepad.exe",
      "img": "https://upload.wikimedia.org/wikipedia/commons/c/c9/Windows_Notepad_icon.png"
    }
  ]
}
